{
  "zh": {
    "titles": ["ID", "版本", "可用"],
    "winget_skip_info": "显式目标",
    "all_latest": "所有应用均为最新版本。",
    "found_updates": "发现有更新的应用，正在准备...",
    "skip_user": "跳过用户指定更新: {appID} [{appVer} -> {appNew}]",
    "force_update": "强制更新: {appID} [{appVer} -> {appNew}]",
    "do_update": "执行更新: {appID} [{appVer} -> {appNew}]",
    "update_success": "更新成功: {appID} [{appNew}]",
    "error": "错误信息: {stderr}",
    "file_not_found": "文件 {file_path} 不存在，使用默认排除列表。",
    "update_done": "于{nowtime}完成更新处理，下一次将在24小时后检查更新。",
    "update_done_custom": "于{nowtime}完成更新处理，下一次将在{interval}后检查更新。",
    "require_admin": "请以管理员身份运行此脚本！",
    "press_enter_exit": "按回车键退出...",
    "launch_app": "启动应用: {app_path}",
    "launch_app_admin": "以管理员身份启动应用: {app_path}",
    "launch_app_error": "无法启动应用 {appID}: {error}",
    "arg_dry_run": "仅预览将要升级的应用，不执行实际升级",
    "arg_once": "只执行一次升级检查，不进入循环",
    "app_description": "AutoUpgradeApp - winget 自动升级工具",
    "upgrade_success_keywords": ["成功", "已成功", "已升级", "已完成"],
    "update_fail": "检测到更新失败: {appID}，winget 输出: {stdout}",
    "proxy_enabled": "已启用代理服务器: {proxy}",
    "proxy_disabled": "未设置代理服务器，使用直连",
    "upgrade_unknown_error": "升级过程中遇到未知错误，请查看winget日志获取详情",
    "check_interval_loaded": "检查间隔设置: {interval}",
    "realtime_upgrade_start": "开始升级 {appID}",
    "realtime_output_separator": "=",
    "realtime_error_output": "错误输出:",
    "realtime_read_remaining_error": "读取剩余输出时出错: {error}",
    "realtime_read_line_error": "读取实时输出时出错: {error}",
    "realtime_read_stderr_error": "读取错误输出时出错: {error}",
    "encoding_fallback_warning": "编码处理失败，使用备用方案",
    "winget_command_failed": "无法执行winget命令: {error}"
  },
  "ja": {
    "titles": ["ID", "バージョン", "利用可能"],
    "winget_skip_info": "明示的ターゲット",
    "all_latest": "すべてのアプリは最新バージョンです。",
    "found_updates": "更新が見つかりました、準備中...",
    "skip_user": "ユーザー指定の更新をスキップ: {appID} [{appVer} -> {appNew}]",
    "force_update": "強制更新: {appID} [{appVer} -> {appNew}]",
    "do_update": "更新を実行: {appID} [{appVer} -> {appNew}]",
    "update_success": "更新成功: {appID} [{appNew}]",
    "error": "エラー情報: {stderr}",
    "file_not_found": "ファイル {file_path} が存在しません。デフォルトの除外リストを使用します。",
    "update_done": "{nowtime}に更新処理が完了しました。次回は24時間後にチェックします。",
    "update_done_custom": "{nowtime}に更新処理が完了しました。次回は{interval}後にチェックします。",
    "require_admin": "管理者権限でこのスクリプトを実行してください！",
    "press_enter_exit": "Enterキーを押して終了...",
    "launch_app": "アプリを起動: {app_path}",
    "launch_app_admin": "管理者権限でアプリを起動: {app_path}",
    "launch_app_error": "アプリ {appID} を起動できません: {error}",
    "arg_dry_run": "アップグレードするアプリをプレビューするだけで、実際のアップグレードは実行しません",
    "arg_once": "1回だけアップグレードチェックを実行し、ループに入らない",
    "app_description": "AutoUpgradeApp - winget 自動アップグレードツール",
    "upgrade_success_keywords": ["成功", "完了", "正常に", "アップグレードされました"],
    "update_fail": "更新失敗を検出: {appID}、winget 出力: {stdout}",
    "proxy_enabled": "プロキシサーバーが有効: {proxy}",
    "proxy_disabled": "プロキシサーバーが設定されていません、直接接続を使用",
    "upgrade_unknown_error": "アップグレード中に不明なエラーが発生しました、詳細についてはwingetログを確認してください",
    "check_interval_loaded": "チェック間隔設定: {interval}",
    "realtime_upgrade_start": "{appID} のアップグレードを開始",
    "realtime_output_separator": "=",
    "realtime_error_output": "エラー出力:",
    "realtime_read_remaining_error": "残り出力の読み取り中にエラー: {error}",
    "realtime_read_line_error": "リアルタイム出力の読み取り中にエラー: {error}",
    "realtime_read_stderr_error": "エラー出力の読み取り中にエラー: {error}",
    "encoding_fallback_warning": "エンコーディング処理に失敗、代替手段を使用",
    "winget_command_failed": "wingetコマンドを実行できません: {error}"
  },
  "en": {
    "titles": ["ID", "Version", "Available"],
    "winget_skip_info": "Explicit Target",
    "all_latest": "All apps are up to date.",
    "found_updates": "Updates found, preparing...",
    "skip_user": "Skip user-specified update: {appID} [{appVer} -> {appNew}]",
    "force_update": "Force update: {appID} [{appVer} -> {appNew}]",
    "do_update": "Updating: {appID} [{appVer} -> {appNew}]",
    "update_success": "Update success: {appID} [{appNew}]",
    "error": "Error: {stderr}",
    "file_not_found": "File {file_path} not found, using default exclude list.",
    "update_done": "Update completed at {nowtime}, next check in 24 hours.",
    "update_done_custom": "Update completed at {nowtime}, next check in {interval}.",
    "require_admin": "Please run this script as administrator!",
    "press_enter_exit": "Press Enter to exit...",
    "launch_app": "Launching application: {app_path}",
    "launch_app_admin": "Launching application as administrator: {app_path}",
    "launch_app_error": "Failed to launch application {appID}: {error}",
    "arg_dry_run": "Preview the apps to be upgraded, do not perform actual upgrade",
    "arg_once": "Perform upgrade check only once, do not enter loop",
    "app_description": "AutoUpgradeApp - winget automatic upgrade tool",
    "upgrade_success_keywords": ["successfully", "completed", "succeeded", "upgraded"],
    "update_fail": "Update failed detected: {appID}, winget output: {stdout}",
    "proxy_enabled": "Proxy server enabled: {proxy}",
    "proxy_disabled": "No proxy server configured, using direct connection",
    "upgrade_unknown_error": "Unknown error occurred during upgrade, please check winget logs for details",
    "check_interval_loaded": "Check interval setting: {interval}",
    "realtime_upgrade_start": "Starting upgrade for {appID}",
    "realtime_output_separator": "=",
    "realtime_error_output": "Error output:",
    "realtime_read_remaining_error": "Error reading remaining output: {error}",
    "realtime_read_line_error": "Error reading real-time output: {error}",
    "realtime_read_stderr_error": "Error reading stderr output: {error}",
    "encoding_fallback_warning": "Encoding handling failed, using fallback method",
    "winget_command_failed": "Unable to execute winget command: {error}"
  }
}
